decorrelator/__init__.py
decorrelator/__version__.py
decorrelator/base.py
decorrelator/correlation.py
decorrelator/estimation.py
decorrelator/linear.py
decorrelator-1.0.0.dist-info/LICENSE
decorrelator-1.0.0.dist-info/METADATA
decorrelator-1.0.0.dist-info/WHEEL
decorrelator-1.0.0.dist-info/top_level.txt
decorrelator-1.0.0.dist-info/RECORD
