Metadata-Version: 2.1
Name: decorrelator
Version: 1.0.0
Summary: Easy-to-use Bayesian full and partial correlation estimator
Home-page: https://github.com/philastrophist/decorrelator
Author: philastrophist
Author-email: shaun.c.read@gmail.com
License: MIT
Platform: UNKNOWN
Classifier: License :: OSI Approved :: MIT License
Classifier: Programming Language :: Python
Classifier: Programming Language :: Python :: 3
Classifier: Programming Language :: Python :: 3.3
Classifier: Programming Language :: Python :: 3.4
Classifier: Programming Language :: Python :: 3.5
Classifier: Programming Language :: Python :: 3.6
Classifier: Programming Language :: Python :: 3.7
Classifier: Programming Language :: Python :: Implementation :: CPython
Classifier: Programming Language :: Python :: Implementation :: PyPy
Requires-Dist: numpy
Requires-Dist: matplotlib
Requires-Dist: tqdm
Requires-Dist: pymc3
Requires-Dist: statsmodels
Requires-Dist: astroML
Requires-Dist: chainconsumer
Requires-Dist: fastkde
